ferret/__init__.py
ferret/cli.py
ferret/core.py
ferret/models.py
ferret/py.typed
ferret/report.py
ferret_io-0.3.1.dist-info/METADATA
ferret_io-0.3.1.dist-info/WHEEL
ferret_io-0.3.1.dist-info/entry_points.txt
ferret_io-0.3.1.dist-info/licenses/LICENSE
ferret_io-0.3.1.dist-info/RECORD
