Metadata-Version: 2.4
Name: ferret-io
Version: 0.3.1
Summary: Async-native, persistent, inter-process performance logger.
Author-email: Alejandro Piad <apiad@apiad.net>
License-File: LICENSE
Requires-Python: >=3.13
Requires-Dist: beaver-db>=1.3.0
